{
  "name": "baseline_plus_local_lineup_features",
  "feature_count": 152,
  "feature_families": [
    "local_lineup"
  ],
  "feature_columns": [
    "elo_home",
    "elo_away",
    "elo_difference",
    "elo_rolling_five_home",
    "elo_rolling_five_away",
    "implied_prob_home",
    "pace_home",
    "pace_away",
    "pace_difference",
    "shooting_pct_home",
    "shooting_pct_away",
    "shooting_pct_diff",
    "home_win_pct_home",
    "road_win_pct_home",
    "games_played_home",
    "home_win_pct_away",
    "road_win_pct_away",
    "games_played_away",
    "home_implied_prob_close",
    "away_implied_prob_close",
    "home_spread_close",
    "market_elo_diff",
    "has_market_odds",
    "sharp_signal_home",
    "spread_movement_pts",
    "open_implied_prob_home",
    "line_movement",
    "h2h_home_win_rate_10",
    "h2h_home_pts_diff_10",
    "home_court_strength_home",
    "home_court_strength_away",
    "ppg_10_home",
    "opp_ppg_10_home",
    "fg_pct_roll_10_home",
    "ft_pct_roll_10_home",
    "fg3_pct_roll_10_home",
    "last_5_win_rate_home",
    "last_10_win_rate_home",
    "win_streak_home",
    "ewm_win_rate_5_home",
    "offensive_rating_home",
    "defensive_rating_home",
    "net_rating_home",
    "turnovers_per_game_home",
    "opponent_off_rating_10_home",
    "opponent_def_rating_10_home",
    "player_impact_estimate_home",
    "player_injury_flag_home",
    "injured_count_home",
    "star_available_home",
    "star_count_home",
    "star_points_lost_home",
    "star_points_lost_missing_home",
    "star_importance_lost_missing_home",
    "rest_days_home",
    "back_to_back_home",
    "fatigue_load_index_home",
    "coaching_adaptability_score_home",
    "coaching_adaptability_score_missing_home",
    "season_pressure_home",
    "ppg_10_away",
    "opp_ppg_10_away",
    "fg_pct_roll_10_away",
    "ft_pct_roll_10_away",
    "fg3_pct_roll_10_away",
    "last_5_win_rate_away",
    "last_10_win_rate_away",
    "win_streak_away",
    "ewm_win_rate_5_away",
    "offensive_rating_away",
    "defensive_rating_away",
    "net_rating_away",
    "turnovers_per_game_away",
    "opponent_off_rating_10_away",
    "opponent_def_rating_10_away",
    "player_impact_estimate_away",
    "player_injury_flag_away",
    "injured_count_away",
    "star_available_away",
    "star_count_away",
    "star_points_lost_away",
    "star_points_lost_missing_away",
    "star_importance_lost_missing_away",
    "rest_days_away",
    "back_to_back_away",
    "fatigue_load_index_away",
    "coaching_adaptability_score_away",
    "coaching_adaptability_score_missing_away",
    "season_pressure_away",
    "elo_diff",
    "net_rating_diff",
    "offensive_rating_diff",
    "defensive_rating_diff",
    "last_5_win_rate_diff",
    "last_10_win_rate_diff",
    "ppg_10_diff",
    "rest_days_diff",
    "fatigue_load_index_diff",
    "turnovers_per_game_diff",
    "player_impact_estimate_diff",
    "injured_count_diff",
    "coaching_adaptability_score_diff",
    "star_points_lost_diff",
    "star_importance_lost_diff",
    "star_expected_minutes_lost_diff",
    "season_pressure_diff",
    "win_streak_diff",
    "ewm_win_rate_5_diff",
    "injury_impact_score_diff",
    "starter_impact_lost_diff",
    "lineup_continuity_5_diff",
    "expected_starter_stability_diff",
    "home_spread_close_missing",
    "sharp_signal_home_missing",
    "book_consensus_std_missing",
    "spread_movement_pts_missing",
    "open_implied_prob_home_missing",
    "line_movement_missing",
    "coaching_adaptability_score_home_missing",
    "coaching_adaptability_score_away_missing",
    "star_points_lost_home_missing",
    "star_points_lost_away_missing",
    "star_importance_lost_home_missing",
    "star_importance_lost_away_missing",
    "starters_available_home",
    "starters_available_away",
    "starters_missing_home",
    "starters_missing_away",
    "top5_minutes_missing_home",
    "top5_minutes_missing_away",
    "top3_scorers_missing_home",
    "top3_scorers_missing_away",
    "starter_minutes_share_lost_home",
    "starter_minutes_share_lost_away",
    "rotation_minutes_share_lost_home",
    "rotation_minutes_share_lost_away",
    "scoring_share_lost_home",
    "scoring_share_lost_away",
    "injury_impact_score_home",
    "injury_impact_score_away",
    "starter_impact_lost_home",
    "starter_impact_lost_away",
    "lineup_continuity_3_home",
    "lineup_continuity_3_away",
    "lineup_continuity_5_home",
    "lineup_continuity_5_away",
    "lineup_continuity_10_home",
    "lineup_continuity_10_away",
    "returning_starter_count_home",
    "returning_starter_count_away",
    "expected_starter_stability_home",
    "expected_starter_stability_away"
  ],
  "dropped_columns": []
}